{
  "type": "MaxHistoryTrackerFeaturizer",
  "state_featurizer": {
    "action_texts": [],
    "entity_tag_specs": [],
    "feature_states": {
      "intent": {
        "affirm": 0,
        "ask_accessibility": 1,
        "ask_age_restrictions": 2,
        "ask_availability": 3,
        "ask_cancellation": 4,
        "ask_contact": 5,
        "ask_date": 6,
        "ask_discounts": 7,
        "ask_dress_code": 8,
        "ask_event_info": 9,
        "ask_food_drinks": 10,
        "ask_location": 11,
        "ask_parking": 12,
        "ask_performers": 13,
        "ask_photography": 14,
        "ask_price": 15,
        "ask_program": 16,
        "ask_seating": 17,
        "ask_social_media": 18,
        "ask_sponsors": 19,
        "ask_terms": 20,
        "ask_ticket_types": 21,
        "ask_time": 22,
        "ask_timing": 23,
        "ask_venue": 24,
        "back": 25,
        "bot_challenge": 26,
        "deny": 27,
        "goodbye": 28,
        "greet": 29,
        "nlu_fallback": 30,
        "out_of_scope": 31,
        "restart": 32,
        "session_start": 33,
        "thank": 34
      },
      "action_name": {
        "action_listen": 0,
        "action_restart": 1,
        "action_session_start": 2,
        "action_default_fallback": 3,
        "action_deactivate_loop": 4,
        "action_revert_fallback_events": 5,
        "action_default_ask_affirmation": 6,
        "action_default_ask_rephrase": 7,
        "action_two_stage_fallback": 8,
        "action_unlikely_intent": 9,
        "action_back": 10,
        "...": 11,
        "action_extract_slots": 12,
        "action_format_datetime": 13,
        "action_get_event_info": 14,
        "action_get_agent_info": 15,
        "action_set_event_context": 16,
        "action_handle_custom_field": 17,
        "utter_date": 18,
        "utter_event_info": 19,
        "utter_price": 20,
        "utter_discounts": 21,
        "utter_availability": 22,
        "utter_accessibility": 23,
        "utter_food_drinks": 24,
        "utter_contact": 25,
        "utter_thank": 26,
        "utter_greet": 27,
        "utter_goodbye": 28,
        "utter_iamabot": 29,
        "utter_fallback": 30,
        "utter_performers": 31,
        "utter_program": 32,
        "utter_timing": 33,
        "utter_photography": 34,
        "utter_venue": 35,
        "utter_seating": 36,
        "utter_age_restrictions": 37,
        "utter_terms": 38,
        "utter_cancellation": 39,
        "utter_parking": 40,
        "utter_location": 41,
        "utter_dress_code": 42,
        "utter_ticket_types": 43,
        "utter_out_of_scope": 44,
        "utter_social_media": 45,
        "utter_sponsors": 46
      },
      "entities": {
        "accessibility": 0,
        "age": 1,
        "capacity": 2,
        "contact": 3,
        "date": 4,
        "detail_type": 5,
        "discount": 6,
        "dress_code": 7,
        "event_name": 8,
        "food": 9,
        "location": 10,
        "parking": 11,
        "performer": 12,
        "policy": 13,
        "price": 14,
        "program": 15,
        "seating": 16,
        "social": 17,
        "sponsor": 18,
        "technical": 19,
        "terms": 20,
        "ticket": 21,
        "time": 22,
        "venue": 23
      },
      "slots": {
        "event_name_0": 0,
        "event_date_0": 1,
        "event_location_0": 2,
        "event_price_0": 3,
        "student_discount_0": 4,
        "military_discount_0": 5,
        "family_discount_0": 6,
        "member_discount_0": 7,
        "start_time_0": 8,
        "end_time_0": 9,
        "doors_open_0": 10,
        "venue_name_0": 11,
        "address_0": 12,
        "contact_person_0": 13,
        "contact_phone_0": 14,
        "contact_email_0": 15,
        "capacity_0": 16,
        "parking_info_0": 17,
        "accessibility_0": 18,
        "age_restriction_0": 19,
        "min_age_0": 20,
        "max_age_0": 21,
        "ticket_types_0": 22,
        "vip_price_0": 23,
        "regular_price_0": 24,
        "performers_0": 25,
        "special_guests_0": 26,
        "food_drinks_0": 27,
        "kosher_info_0": 28,
        "cancellation_policy_0": 29,
        "refund_policy_0": 30,
        "photography_policy_0": 31,
        "recording_policy_0": 32,
        "seating_type_0": 33,
        "sound_system_0": 34,
        "stage_info_0": 35,
        "program_0": 36,
        "social_media_0": 37,
        "hashtags_0": 38,
        "sponsors_0": 39,
        "partners_0": 40,
        "terms_conditions_0": 41,
        "agent_name_0": 42,
        "agent_style_0": 43,
        "agent_expertise_0": 44,
        "requested_ticket_type_0": 45,
        "requested_accessibility_0": 46,
        "has_food_interest_0": 47,
        "has_food_interest_1": 48,
        "requested_discount_0": 49,
        "price_info_0": 50
      },
      "active_loop": {}
    }
  },
  "remove_duplicates": true,
  "max_history": 5
}