{
  "type": "MaxHistoryTrackerFeaturizer",
  "state_featurizer": {
    "action_texts": [],
    "entity_tag_specs": [],
    "feature_states": {
      "intent": {
        "affirm": 0,
        "ask_about_agent": 1,
        "ask_about_discounts": 2,
        "ask_accessibility": 3,
        "ask_age_restrictions": 4,
        "ask_capabilities": 5,
        "ask_capacity": 6,
        "ask_contact_info": 7,
        "ask_covid_policy": 8,
        "ask_dress_code": 9,
        "ask_duration": 10,
        "ask_event_date": 11,
        "ask_event_info": 12,
        "ask_event_link": 13,
        "ask_event_location": 14,
        "ask_event_price": 15,
        "ask_event_quality": 16,
        "ask_family_discount": 17,
        "ask_food_info": 18,
        "ask_general_discounts": 19,
        "ask_group_discount": 20,
        "ask_how_to_pay": 21,
        "ask_media_policy": 22,
        "ask_member_discount": 23,
        "ask_military_discount": 24,
        "ask_organizer_info": 25,
        "ask_parking_info": 26,
        "ask_payment_methods": 27,
        "ask_performers": 28,
        "ask_performers_info": 29,
        "ask_refund_policy": 30,
        "ask_schedule": 31,
        "ask_security_measures": 32,
        "ask_social_media": 33,
        "ask_sponsors_partners": 34,
        "ask_student_discount": 35,
        "ask_technical_info": 36,
        "ask_tickets_left": 37,
        "ask_vip_options": 38,
        "back": 39,
        "bot_challenge": 40,
        "deny": 41,
        "express_confusion": 42,
        "goodbye": 43,
        "greet": 44,
        "nlu_fallback": 45,
        "out_of_scope": 46,
        "restart": 47,
        "session_start": 48,
        "thank": 49
      },
      "action_name": {
        "action_listen": 0,
        "action_restart": 1,
        "action_session_start": 2,
        "action_default_fallback": 3,
        "action_deactivate_loop": 4,
        "action_revert_fallback_events": 5,
        "action_default_ask_affirmation": 6,
        "action_default_ask_rephrase": 7,
        "action_two_stage_fallback": 8,
        "action_unlikely_intent": 9,
        "action_back": 10,
        "...": 11,
        "action_extract_slots": 12,
        "action_check_age_restrictions": 13,
        "utter_about_agent": 14,
        "utter_accessibility": 15,
        "utter_age_restrictions": 16,
        "utter_age_restrictions_no_max": 17,
        "utter_capacity": 18,
        "utter_clarify_age_restrictions": 19,
        "utter_clarify_capacity": 20,
        "utter_clarify_quality": 21,
        "utter_covid_policy": 22,
        "utter_default": 23,
        "utter_dress_code": 24,
        "utter_duration": 25,
        "utter_event_date": 26,
        "utter_event_info": 27,
        "utter_event_link": 28,
        "utter_event_location": 29,
        "utter_event_price": 30,
        "utter_event_quality": 31,
        "utter_family_discount": 32,
        "utter_food_info": 33,
        "utter_general_discounts": 34,
        "utter_goodbye": 35,
        "utter_greet": 36,
        "utter_group_discount": 37,
        "utter_how_to_pay": 38,
        "utter_iamabot": 39,
        "utter_member_discount": 40,
        "utter_military_discount": 41,
        "utter_parking_info": 42,
        "utter_payment_methods": 43,
        "utter_performers": 44,
        "utter_performers_info": 45,
        "utter_refund_policy": 46,
        "utter_schedule": 47,
        "utter_security_measures": 48,
        "utter_social_media": 49,
        "utter_sponsors_partners": 50,
        "utter_student_discount": 51,
        "utter_technical_info": 52,
        "utter_thank": 53,
        "utter_tickets_left": 54,
        "utter_vip_options": 55
      },
      "entities": {},
      "slots": {},
      "active_loop": {}
    }
  },
  "remove_duplicates": true,
  "max_history": 5
}